LICENSE
MANIFEST.in
README.md
setup.py
drf_accountkit/__init__.py
drf_accountkit/admin.py
drf_accountkit/apps.py
drf_accountkit/models.py
drf_accountkit/tests.py
drf_accountkit/urls.py
drf_accountkit/views.py
drf_accountkit.egg-info/PKG-INFO
drf_accountkit.egg-info/SOURCES.txt
drf_accountkit.egg-info/dependency_links.txt
drf_accountkit.egg-info/top_level.txt
drf_accountkit/migrations/__init__.py