Metadata-Version: 1.1
Name: drf-accountkit
Version: 0.2.3
Summary: DRF AccountKit is the wrapper to use facebook account kit to authenticate first time in Django REST Framework
Home-page: https://github.com/assem-ch/drf-accountkit
Author: Assem Chelli
Author-email: assem.ch@gmail.com
License: MIT License
Platform: UNKNOWN
Classifier: Environment :: Web Environment
Classifier: Framework :: Django
Classifier: Framework :: Django :: 2.0
Classifier: Intended Audience :: Developers
Classifier: License :: OSI Approved :: BSD License
Classifier: Operating System :: OS Independent
Classifier: Programming Language :: Python
Classifier: Programming Language :: Python :: 2.7
Classifier: Programming Language :: Python :: 3.5
Classifier: Programming Language :: Python :: 3.6
Classifier: Topic :: Internet :: WWW/HTTP
Classifier: Topic :: Internet :: WWW/HTTP :: Dynamic Content
